src/alu.sv
module alu #(
  parameter  WIDTH     = 8,
  localparam W_ALU_SEL = 3
)(
  input  logic signed [WIDTH-1:0] bus_a,
  input  logic signed [WIDTH-1:0] bus_b,
  output logic signed [WIDTH-1:0] alu_out,
  input  logic [W_ALU_SEL   -1:0] alu_sel,
  output logic zero, negative
);

//  always_comb begin
//    if (alu_sel == 3'b000) alu_out = bus_a +  bus_b;
//    else if (alu_sel == W_ALU_SEL'b001) alu_out = bus_a -  bus_b;
//    else if (alu_sel == W_ALU_SEL'b010) alu_out = bus_a *  bus_b;
//    else if (alu_sel == W_ALU_SEL'b011 & bus_b != WIDTH'b00000000) alu_out = bus_a /  bus_b;
//    else if (alu_sel == W_ALU_SEL'b100  & bus_b != 2'h00) alu_out = bus_a % bus_b;
//    else                       alu_out = bus_a;  // pass a if 0
//end

//Usually Use Switch case as MULTIPLEXER
  always_comb begin
    case (alu_sel)
      3'b000: alu_out = bus_a + bus_b;
      3'b001: alu_out = bus_a - bus_b;
      3'b010: alu_out = bus_a * bus_b;
      3'b011: alu_out = (bus_b != 0) ? (bus_a / bus_b) : '0;
      3'b100: alu_out = (bus_b != 0) ? (bus_a % bus_b) : '0;
      default: alu_out = bus_a; // pass a if 0
    endcase
  end

  assign zero     = (alu_out == 0);
  assign negative = (alu_out < 0);

endmodule

src/alu_tb.sv
class Random_Num #(WIDTH);
  rand bit signed [WIDTH-1:0] num;
endclass

class Random_Sel;
  rand bit [2:0] num;
  constraint c {num inside {[0:4]};}

  function new();
    this.randomize();
  endfunction
endclass

module alu_tb();
  timeunit 1ns/1ps;
  logic clk = 0;
  localparam CLK_PERIOD = 10;

  initial begin
    forever #(CLK_PERIOD/2) clk = ~clk;
  end

  localparam WIDTH = 8;
  logic        [2:0]       alu_sel;
  logic signed [WIDTH-1:0] bus_a, bus_b, alu_out;
  logic                    zero, negative;

  alu #(.WIDTH(WIDTH)) dut (
    .bus_a(bus_a),
    .bus_b(bus_b),
    .alu_out(alu_out),
    .alu_sel(alu_sel),
    .zero(zero),
    .negative(negative)
  );

  Random_Num #(WIDTH) A_r = new();
  Random_Num #(WIDTH) B_r = new();
  Random_Sel sel_r = new();

  initial begin
    bus_a <= 8'd5;
    bus_b <= 8'd0;
    alu_sel <= 3'b011;

    #10;
    bus_a <= 8'd30; 
    bus_b <= -8'd10; 
    alu_sel <= 3'b001;

//    @(posedge clk);
#10;
    bus_a <= 8'd5; 
    bus_b <= 8'd10; 
    alu_sel <= 3'b010;

//    @(posedge clk);
#10;
    bus_a <= 8'd51; 
    bus_b <= 8'd17; 
    alu_sel <= 3'b011;

    repeat(5) begin
//      @(posedge clk);
#10;
      A_r.randomize();
      B_r.randomize();
      sel_r.randomize();
      bus_a <= A_r.num; 
      bus_b <= B_r.num; 
      alu_sel <= sel_r.num;
    end
  end

  initial begin
    $dumpfile("dump.vcd"); 
    $dumpvars(0, alu_tb);
  end
endmodule

projects/Com_ALU/Com_ALU.sim/sim_1/behav/xsim/dump.vcd
$date
   Sat May 18 14:38:52 2024
$end

$version
  2023.2
  $dumpfile ("dump.vcd") 
$end

$timescale
  1ps
$end

$scope module alu_tb $end
$var reg 1 ! clk $end
$var reg 3 " alu_sel [2:0] $end
$var reg 8 # bus_a [7:0] $end
$var reg 8 $ bus_b [7:0] $end
$var reg 8 % alu_out [7:0] $end
$var reg 1 & zero $end
$var reg 1 ' negative $end
$var reg 32 ( A_r $end
$var reg 32 ) B_r $end
$var reg 32 * sel_r $end
$scope module dut $end
$var wire 8 + bus_a [7:0] $end
$var wire 8 , bus_b [7:0] $end
$var reg 8 % alu_out [7:0] $end
$var wire 3 - alu_sel [2:0] $end
$var reg 1 & zero $end
$var reg 1 ' negative $end
$upscope $end
$upscope $end
$enddefinitions $end

#0
$dumpvars
0!
b11 "
b101 #
b0 $
b0 %
1&
0'
b100001110000010000000000111000 (
b100001110000010000000001100000 )
b100001110000010000000010001000 *
b101 +
b0 ,
b11 -
$end

#5000
1!

#10000
0!
b1 "
b11110 #
b11110110 $
b101000 %
0&
b11110 +
b11110110 ,
b1 -

#15000
1!

#20000
0!
b10 "
b101 #
b1010 $
b110010 %
b101 +
b1010 ,
b10 -

#25000
1!

#30000
0!
b11 "
b110011 #
b10001 $
b11 %
b110011 +
b10001 ,
b11 -

#35000
1!

#40000
0!
b1 "
b10111111 #
b11000100 $
b11111011 %
1'
b10111111 +
b11000100 ,
b1 -

#45000
1!

#50000
0!
b0 "
b11011000 #
b1011001 $
b110001 %
0'
b11011000 +
b1011001 ,
b0 -

#55000
1!

#60000
0!
b100 "
b10110011 #
b10001100 $
b100111 %
b10110011 +
b10001100 ,
b100 -

#65000
1!

#70000
0!
b1 "
b10110101 #
b10100011 $
b10010 %
b10110101 +
b10100011 ,
b1 -

#75000
1!

#80000
0!
b11 "
b10001011 #
b10010110 $
b0 %
1&
b10001011 +
b10010110 ,
b11 -

